{
  "main": [
    {
      "title": "Home",
      "url": "/"
    },
    {
      "title": "Services",
      "url": "/services/",
      "submenu": [
        {
          "title": "Residential",
          "url": "/services/residential/",
          "items": [
            {"title": "Spray Foam Insulation", "url": "/services/residential/spray-foam/"},
            {"title": "Blown-In Insulation", "url": "/services/residential/blown-in/"},
            {"title": "Dense Pack Insulation", "url": "/services/residential/dense-pack/"},
            {"title": "Attic Insulation", "url": "/services/residential/attic/"},
            {"title": "Wall Insulation", "url": "/services/residential/wall/"},
            {"title": "Crawl Space Insulation", "url": "/services/residential/crawl-space/"},
            {"title": "Insulation Removal", "url": "/services/residential/removal/"}
          ]
        },
        {
          "title": "Commercial",
          "url": "/services/commercial/",
          "items": [
            {"title": "Office Buildings", "url": "/services/commercial/office/"},
            {"title": "Retail Spaces", "url": "/services/commercial/retail/"},
            {"title": "Warehouses", "url": "/services/commercial/warehouse/"},
            {"title": "New Construction", "url": "/services/commercial/new-construction/"}
          ]
        },
        {
          "title": "Industrial",
          "url": "/services/industrial/",
          "items": [
            {"title": "Manufacturing Facilities", "url": "/services/industrial/manufacturing/"},
            {"title": "Cold Storage", "url": "/services/industrial/cold-storage/"},
            {"title": "Equipment Insulation", "url": "/services/industrial/equipment/"}
          ]
        },
        {
          "title": "Agricultural",
          "url": "/services/agricultural/",
          "items": [
            {"title": "Tank Insulation", "url": "/services/agricultural/tank/"},
            {"title": "Barn Insulation", "url": "/services/agricultural/barn/"},
            {"title": "Storage Facilities", "url": "/services/agricultural/storage/"}
          ]
        },
        {
          "title": "Air Duct Cleaning",
          "url": "/services/air-duct-cleaning/"
        },
        {
          "title": "Arizona Insulation Contractor",
          "url": "/insulation-contractor-arizona/"
        },
        {
          "title": "Local Service Areas",
          "url": "/service-areas/",
          "items": [
            {"title": "Phoenix Insulation Services", "url": "/phoenix-insulation-services/"},
            {"title": "Mesa Insulation Services", "url": "/mesa-insulation-services/"},
            {"title": "Chandler Insulation Services", "url": "/chandler-insulation-services/"},
            {"title": "Scottsdale Insulation Services", "url": "/scottsdale-insulation-services/"},
            {"title": "Gilbert Insulation Services", "url": "/gilbert-insulation-services/"},
            {"title": "Glendale Insulation Services", "url": "/glendale-insulation-services/"},
            {"title": "Tempe Insulation Services", "url": "/tempe-insulation-services/"}
          ]
        }
      ]
    },
    {
      "title": "Products",
      "url": "/products/",
      "submenu": [
        {
          "title": "Spray Foam Hub",
          "url": "/spray-foam-insulation-phoenix/",
          "items": [
            {"title": "Cost Calculator", "url": "/spray-foam-hub/spray-foam-cost-calculator/"},
            {"title": "Open vs Closed Cell", "url": "/spray-foam-hub/open-cell-vs-closed-cell/"},
            {"title": "R-Value Guide", "url": "/spray-foam-r-value-guide/"},
            {"title": "Installation Process", "url": "/spray-foam-installation-process/"},
            {"title": "Find Contractors", "url": "/spray-foam-contractors-near-me/"}
          ]
        },
        {
          "title": "Spray Foam Types",
          "items": [
            {"title": "Open Cell Spray Foam", "url": "/products/open-cell-spray-foam/"},
            {"title": "Closed Cell Spray Foam", "url": "/products/closed-cell-spray-foam/"}
          ]
        },
        {
          "title": "Traditional Insulation",
          "items": [
            {"title": "Fiberglass Batts", "url": "/products/fiberglass-batts/"},
            {"title": "Cellulose", "url": "/products/cellulose/"},
            {"title": "Mineral Wool", "url": "/products/mineral-wool/"}
          ]
        },
        {
          "title": "Air Sealing Products",
          "url": "/products/air-sealing/"
        }
      ]
    },
    {
      "title": "Blog",
      "url": "/blog/"
    },
    {
      "title": "About Us",
      "url": "/about/",
      "submenu": [
        {"title": "Our Story", "url": "/about/"},
        {"title": "Events", "url": "/about/events/"},
        {"title": "Community", "url": "/about/community/"}
      ]
    },
    {
      "title": "Contact",
      "url": "/contact/",
      "class": "cta-button"
    }
  ]
}